exclusionms/__init__.py
exclusionms/apihandler.py
exclusionms/components.py
exclusionms/db.py
exclusionms/offlinehandler.py
exclusionms/random.py
exclusionms/stress_test.py
exclusionms-0.4.1.dist-info/LICENSE
exclusionms-0.4.1.dist-info/METADATA
exclusionms-0.4.1.dist-info/WHEEL
exclusionms-0.4.1.dist-info/entry_points.txt
exclusionms-0.4.1.dist-info/top_level.txt
exclusionms-0.4.1.dist-info/RECORD
