Metadata-Version: 2.1
Name: exclusionms
Version: 0.4.1
Summary: Python package for working with exclusionms-api and exclusionms-streamlit
Author-email: Patrick Garrett <pgarrett@scripps.edu>
License: MIT License
Project-URL: home, https://github.com/pgarrett-scripps/ExclusionMs.git
Classifier: Programming Language :: Python :: 3
Classifier: Development Status :: 4 - Beta
Classifier: License :: OSI Approved :: MIT License
Classifier: Operating System :: OS Independent
Requires-Python: >=3.8
License-File: LICENSE
Requires-Dist: intervaltree
Requires-Dist: requests
Requires-Dist: pydantic
Requires-Dist: ujson
Requires-Dist: matplotlib
Requires-Dist: numpy
